{
  "fund_name": "Parag Parikh Flexi Cap Fund - Direct Growth",
  "aum": "\u20b987,539.41 Cr",
  "sector_allocation": {
    "investment objective of the Scheme will be achieved and Debt and Money Market Instruments": 9.77,
    "Finance": 7.31,
    "Type of the Scheme Power": 6.54,
    "Automobiles": 5.76,
    "Diversified FMCG": 5.47,
    "Pharmaceuticals & Biotechnology": 3.65,
    "Managers Arbitrage/Special Situation": 1.36,
    "Fertilizers & Agrochemicals": 0.23,
    "Healthcare Services": 0.19
  },
  "category_allocation": {
    "Overseas Equity": 8.76,
    "Indian Equity": 91.24
  },
  "extraction_date": "2026-04-03",
  "pages_parsed": "pages 2-3",
  "source_url": "https://amc.ppfas.com/downloads/factsheet/2024/ppfas-mf-factsheet-for-December-2024.pdf",
  "factsheet_month": "December 2024"
}